{
 "pageNumber": 567,
 "printedPageNumber": "563",
 "width": 1735,
 "height": 2500,
 "unit": "pixel",
 "markdown": "\n<div style=\"text-align: center;\"><html><body><table border=\"1\"><tr><td>年代</td><td>法令</td><td>ないよう 内容·特色</td></tr><tr><td>604年 701年 743年 1232年 1297年 戦国時代 1588年 1615年 1825年 1868年 1889年 1925年 1946年</td><td>じうしちじよう けんぽう 十七条の憲法 たいほうりつりよう 大宝律令 こんでんえいねんしさいのほう 墾田永年私財法 ごせいばいしきもく 御成敗式目 えいにん とくせいれい 永仁の徳政令 ぶんこほうかほう 分国法（家法） りれい 刀狩令 ぶけしよはつと 武家諸法度 いこくせんうちはいれい 异国船打払令 こかしよう こせいん 五箇条の御誓文 202 大日本帝国憲法 治安維持法 日本国憲法</td><td>しようとくたいし せいてい がま しめ 聖徳太子が制定。役人の心構えを示した。 ふじわのふひと へんう けいほう ぎうせいほう 藤原不比等らが編集。律は刑法、令は行政法など。 えいきゆう みと 新たに開墾した土地の永久私有を認めた。 ほうじようやすとき ぶ 北条泰時が制定。武士がつくった最初の法律。 ごけにん 御家人の借金の帳消しなどを定めた。 りようごく しはい 戦国大名が領国を支配するために定めた。 とよとみひでよし ひや<しょう 豊臣秀吉が制定。百姓から武器を取りあげた。 えどばくふ だいようとうせい 江戸幕府が大名統制のために定めた。 しん げきたい 江戸幕府がオランダ・清以外の外国船撃退を命じた。 めいじ きほんほうしん 明治新政府が定めた政治の基本方針。 てんのうしゆけん しき 天皇主権。天皇が国の統治権や軍隊の指揮権をもった。 しゆぎ 社会主義運動を取りしまるために定められた。 んちよう げんそく 国民主権・基本的人権の尊重・平和主義が三大原則。</td></tr></table></body></html></div>\n\n\n## 14 おもな法令\n\n\n\n政\n\n治\n\n\n\n中牌\n\n2\n\n\n\n## 1 おもな外国との条約・できごと\n\n\n<div style=\"text-align: center;\"><html><body><table border=\"1\"><tbody><tr><td>年代</td><td>じうやく 条約・できごと</td><td>内容·特色</td></tr><tr><td>1854年 1858年 1895年 1895年 1905年 1910年 1945年 1951年 1951年 1956年 1965年 1972年 1978年</td><td>日米和親条約 しうこう 日米修好通商条約 しものせき 下関条約 さんごくかんしよう 三国干渉 ポーツマス条約 かんこくへいごう 韓国併合 せんげん ポツダム宣言 サンフランシス コ平和条約 しょう 日米安全保障条約 日ソ共同宣言 日韓基本条約 日中共同声明 日中平和友好条約</td><td>しもだ はこだて ペリ一と江戸幕府が結んだ条約。下田・函館を開港。 かんぜい りようじさいばんけん 関税自主権がなく、領事裁判権を認めた不平等条約。 につしん こうわ リアオトン かくとく 日清戦争の講和条約。日本は遼東半島などを獲得。 りようとう へんかん ロシア・ドイツ・フランスが遼東半島の返還を要求。 にちろ ちゆうかい 日露戦争の講和条約。アメリ力の仲介で結ばれた。 ちようせんそうとくふ 日本が韓国を併合し、朝鮮総督府を置いた。 むじようけんこうふく 連合国が日本に無条件降伏を求めた。 よくねん どくりつ かいふく 日本と連合国の講和条約。翌年、日本は独立を回復。 独立後もアメリ力軍が日本にとどまることを認めた。 こくさい かめい 日ソ間の国交が回復。同年、日本は国際連合に加盟。 ゆいいつ 韓国を朝鮮半島における唯一の合法的政府と認めた。 せいじょう じつげん 日中間の国交正常化が実現した。 けいざい はってん そくしん 経済・文化の発展や交流の促進などを定めた。</td></tr></tbody></table></body></html></div>\n",
 "blocks": [
  {
   "id": "p0567_b00",
   "type": "aside_text",
   "bbox": [
    11,
    44,
    115,
    2467
   ]
  },
  {
   "id": "p0567_b01",
   "type": "table",
   "bbox": [
    163,
    260,
    1536,
    1176
   ],
   "content": "<html><body><table><tr><td>年代</td><td>法令</td><td>ないよう 内容·特色</td></tr><tr><td>604年 701年 743年 1232年 1297年 戦国時代 1588年 1615年 1825年 1868年 1889年 1925年 1946年</td><td>じうしちじよう けんぽう 十七条の憲法 たいほうりつりよう 大宝律令 こんでんえいねんしさいのほう 墾田永年私財法 ごせいばいしきもく 御成敗式目 えいにん とくせいれい 永仁の徳政令 ぶんこほうかほう 分国法（家法） りれい 刀狩令 ぶけしよはつと 武家諸法度 いこくせんうちはいれい 异国船打払令 こかしよう こせいん 五箇条の御誓文 202 大日本帝国憲法 治安維持法 日本国憲法</td><td>しようとくたいし せいてい がま しめ 聖徳太子が制定。役人の心構えを示した。 ふじわのふひと へんう けいほう ぎうせいほう 藤原不比等らが編集。律は刑法、令は行政法など。 えいきゆう みと 新たに開墾した土地の永久私有を認めた。 ほうじようやすとき ぶ 北条泰時が制定。武士がつくった最初の法律。 ごけにん 御家人の借金の帳消しなどを定めた。 りようごく しはい 戦国大名が領国を支配するために定めた。 とよとみひでよし ひや<しょう 豊臣秀吉が制定。百姓から武器を取りあげた。 えどばくふ だいようとうせい 江戸幕府が大名統制のために定めた。 しん げきたい 江戸幕府がオランダ・清以外の外国船撃退を命じた。 めいじ きほんほうしん 明治新政府が定めた政治の基本方針。 てんのうしゆけん しき 天皇主権。天皇が国の統治権や軍隊の指揮権をもった。 しゆぎ 社会主義運動を取りしまるために定められた。 んちよう げんそく 国民主権・基本的人権の尊重・平和主義が三大原則。</td></tr></table></body></html>",
   "tableId": "tbl_p0567_01"
  },
  {
   "id": "p0567_b02",
   "type": "heading",
   "bbox": [
    311,
    139,
    797,
    220
   ],
   "content": "14おもな法令"
  },
  {
   "id": "p0567_b03",
   "type": "paragraph",
   "bbox": [
    1618,
    260,
    1714,
    373
   ]
  },
  {
   "id": "p0567_b04",
   "type": "paragraph",
   "bbox": [
    1618,
    408,
    1714,
    521
   ],
   "content": "政\n\n治"
  },
  {
   "id": "p0567_b05",
   "type": "paragraph",
   "bbox": [
    1619,
    555,
    1716,
    815
   ],
   "content": "中牌\n\n2"
  },
  {
   "id": "p0567_b06",
   "type": "pageHeader",
   "bbox": [
    1620,
    119,
    1711,
    205
   ],
   "content": "資料編"
  },
  {
   "id": "p0567_b07",
   "type": "heading",
   "bbox": [
    304,
    1235,
    1425,
    1319
   ],
   "content": "1おもな外国との条約・できごと"
  },
  {
   "id": "p0567_b08",
   "type": "table",
   "bbox": [
    167,
    1362,
    1537,
    2326
   ],
   "content": "<html><body><table><tbody><tr><td>年代</td><td>じうやく 条約・できごと</td><td>内容·特色</td></tr><tr><td>1854年 1858年 1895年 1895年 1905年 1910年 1945年 1951年 1951年 1956年 1965年 1972年 1978年</td><td>日米和親条約 しうこう 日米修好通商条約 しものせき 下関条約 さんごくかんしよう 三国干渉 ポーツマス条約 かんこくへいごう 韓国併合 せんげん ポツダム宣言 サンフランシス コ平和条約 しょう 日米安全保障条約 日ソ共同宣言 日韓基本条約 日中共同声明 日中平和友好条約</td><td>しもだ はこだて ペリ一と江戸幕府が結んだ条約。下田・函館を開港。 かんぜい りようじさいばんけん 関税自主権がなく、領事裁判権を認めた不平等条約。 につしん こうわ リアオトン かくとく 日清戦争の講和条約。日本は遼東半島などを獲得。 りようとう へんかん ロシア・ドイツ・フランスが遼東半島の返還を要求。 にちろ ちゆうかい 日露戦争の講和条約。アメリ力の仲介で結ばれた。 ちようせんそうとくふ 日本が韓国を併合し、朝鮮総督府を置いた。 むじようけんこうふく 連合国が日本に無条件降伏を求めた。 よくねん どくりつ かいふく 日本と連合国の講和条約。翌年、日本は独立を回復。 独立後もアメリ力軍が日本にとどまることを認めた。 こくさい かめい 日ソ間の国交が回復。同年、日本は国際連合に加盟。 ゆいいつ 韓国を朝鮮半島における唯一の合法的政府と認めた。 せいじょう じつげん 日中間の国交正常化が実現した。 けいざい はってん そくしん 経済・文化の発展や交流の促進などを定めた。</td></tr></tbody></table></body></html>",
   "tableId": "tbl_p0567_02"
  },
  {
   "id": "p0567_b09",
   "type": "pageNumber",
   "bbox": [
    1617,
    2407,
    1676,
    2443
   ],
   "content": "563"
  }
 ]
}